source_commcare/__init__.py
source_commcare/run.py
source_commcare/schemas/TODO.md
source_commcare/source.py
source_commcare/spec.yaml
airbyte_source_commcare-0.1.39.dist-info/METADATA
airbyte_source_commcare-0.1.39.dist-info/WHEEL
airbyte_source_commcare-0.1.39.dist-info/entry_points.txt
airbyte_source_commcare-0.1.39.dist-info/RECORD
